gunshotmatch_pipeline/decision_tree/__init__.py
gunshotmatch_pipeline/decision_tree/export.py
gunshotmatch_pipeline/decision_tree/predictions.py
gunshotmatch_pipeline/__init__.py
gunshotmatch_pipeline/config.py
gunshotmatch_pipeline/excluded_peaks.py
gunshotmatch_pipeline/exporters.py
gunshotmatch_pipeline/nist_ms_search.py
gunshotmatch_pipeline/peaks.py
gunshotmatch_pipeline/projects.py
gunshotmatch_pipeline/py.typed
gunshotmatch_pipeline/results.py
gunshotmatch_pipeline/unknowns.py
gunshotmatch_pipeline/utils.py
gunshotmatch_pipeline-0.11.0.dist-info/LICENSE
gunshotmatch_pipeline-0.11.0.dist-info/METADATA
gunshotmatch_pipeline-0.11.0.dist-info/WHEEL
gunshotmatch_pipeline-0.11.0.dist-info/entry_points.txt
gunshotmatch_pipeline-0.11.0.dist-info/RECORD
