Metadata-Version: 2.2
Name: gunshotmatch-pipeline
Version: 0.11.0
Summary: GunShotMatch Analysis Pipeline
Author-email: Dominic Davis-Foster <dominic@davis-foster.co.uk>
License: MIT
Home-page: https://github.com/GunShotMatch/gunshotmatch-pipeline
Project-URL: Issue Tracker, https://github.com/GunShotMatch/gunshotmatch-pipeline/issues
Project-URL: Source Code, https://github.com/GunShotMatch/gunshotmatch-pipeline
Project-URL: Documentation, https://gunshotmatch-pipeline.readthedocs.io/en/latest
Platform: Linux
Platform: Windows
Classifier: License :: OSI Approved :: MIT License
Classifier: Operating System :: Microsoft :: Windows
Classifier: Operating System :: POSIX :: Linux
Classifier: Programming Language :: Python
Classifier: Programming Language :: Python :: 3 :: Only
Classifier: Programming Language :: Python :: 3.8
Classifier: Programming Language :: Python :: 3.9
Classifier: Programming Language :: Python :: 3.10
Classifier: Programming Language :: Python :: 3.11
Classifier: Programming Language :: Python :: 3.12
Classifier: Programming Language :: Python :: Implementation :: CPython
Classifier: Typing :: Typed
Requires-Python: >=3.8
Requires-Dist: attrs>=23.1.0
Requires-Dist: domdf-python-tools>=3.6.1
Requires-Dist: graphviz>=0.20.1
Requires-Dist: libgunshotmatch>=0.4.0
Requires-Dist: numpy>=1.22
Requires-Dist: pandas>=2.0.3
Requires-Dist: pymassspec>=2.3.0
Requires-Dist: pyms-nist-search>=0.6.3.post1
Requires-Dist: scikit-learn>=1.3.2
Requires-Dist: sdjson>=0.4.0
Requires-Dist: tomli>=1.2.3; python_version < "3.11"
Requires-Dist: tomli-w>=1.0.0
Requires-Dist: typing-extensions>=4.8.0
